dbt_score/__init__.py
dbt_score/__main__.py
dbt_score/cli.py
dbt_score/config.py
dbt_score/dbt_utils.py
dbt_score/evaluation.py
dbt_score/exceptions.py
dbt_score/lint.py
dbt_score/models.py
dbt_score/more_itertools.py
dbt_score/rule.py
dbt_score/rule_catalog.py
dbt_score/rule_filter.py
dbt_score/rule_registry.py
dbt_score/scoring.py
dbt_score/formatters/__init__.py
dbt_score/formatters/ascii_formatter.py
dbt_score/formatters/human_readable_formatter.py
dbt_score/formatters/json_formatter.py
dbt_score/formatters/manifest_formatter.py
dbt_score/rules/__init__.py
dbt_score/rules/filters.py
dbt_score/rules/generic.py
dbt_score/rules/macros.py
dbt_score-0.15.0.dist-info/METADATA
dbt_score-0.15.0.dist-info/WHEEL
dbt_score-0.15.0.dist-info/entry_points.txt
dbt_score-0.15.0.dist-info/licenses/LICENSE.txt
dbt_score-0.15.0.dist-info/RECORD
