Metadata-Version: 2.4
Name: dbt-score
Version: 0.15.0
Summary: Linter for dbt metadata.
Author-email: Picnic Analyst Development Platform <analyst-development-platform@teampicnic.com>
License: MIT
License-File: LICENSE.txt
Classifier: Intended Audience :: Developers
Classifier: License :: OSI Approved :: MIT License
Classifier: Operating System :: OS Independent
Classifier: Programming Language :: Python
Classifier: Programming Language :: Python :: 3 :: Only
Classifier: Programming Language :: Python :: 3.10
Classifier: Programming Language :: Python :: 3.11
Classifier: Programming Language :: Python :: 3.12
Classifier: Programming Language :: Python :: 3.13
Requires-Python: >=3.10
Requires-Dist: click<9.0.0,>=7.1.1
Requires-Dist: tomli>=1.1.0; python_version < '3.11'
